{
	"groups": [
		{
			"keys": "description_json,close_png,back_1_png,1_png,2_png,3_png,4_png,5_png,logo_png,12_png,22_png,adLogin_png,beijing_jpg,fastLogin_png,kefu_png,loading1_png,loading2_png,示意标注_png,13_png,23_png,32_png,42_png,52_png,6_png,help_png,zha_png,打牌2_png,打牌1_png,cm1_png,cm2_png,cm3_png,cm4_png,cm5_png,cm6_png,cm7_png,cm8_png,WIN_png,倒计时_png,切换房间_png,发 送_png,广播_png,广播底_png,庄平倍_png,庄翻倍_png,无牛_png,筹码底_png,筹码选中光_png,箭头1_png,箭头2_png,结算中_png,聊天_png,聊天底_png,蓝_png,表情_png,规则_png,视频_png,设置_png,路子图_png,路子图2_png,返回底_png,金币_png,金币底_png,问号_png,闲1平倍_png,闲1翻倍_png,闲2平倍_png,闲2翻倍_png,闲3平倍_png,闲3翻倍_png,黄_png,圆角矩形 666 拷贝 4_png,登 录_png,登录_png,获取验证码_png,标注_png,设置标注_png,音乐_png,X_png,底_png,点_png,聊天 copy_png,设置标注2_png,声音_png,视频2_png,系统设置_png,现场_png,小弹窗通用底_png,选房间标注_png,限红_png,jinbi_png,底2_png,金币底2_png,开始_png,头像底_png,图层 602_png,选择房间3_png,选择房间1_png,选择房间2_png,和_png,大_png,大1_png,小1_png,小2_png,小圈_png,小圈2_png,小红_png,小蓝_png,庄_png,斜杠_png,闲_png,龙虎百家乐底_png,14_png,24_png,33_png,43_png,53_png,62_png,大小点底_png,WIN2_png,庄2_png,底3_png,没牛底_png,牛N底_png,牛牛底_png,闲1_png,闲2_png,闲3_png,WIN1_png,凤_png,凤2_png,椭圆 1310 拷贝 2_png,椭圆 1310_png,炸金花_png,龙_png,龙2_png,按钮_png,结算中底_png,金币2_png,金币底3_png,时间图标_png,头像适配_png,下注中底_png,选择房间_png,大厅标注_png,0_png,15_png,25_png,34_png,44_png,54_png,63_png,7_png,8_png,9_png,d_png,+_png,beijing2_jpg,gb_png,VIP  _png,百家乐_png,绑定_png,北京赛车_png,大小点_png,单双_png,公告_png,广告_png,广告点_png,广告点选中_png,滚动条底_png,红点_png,滑动_png,活动_png,金币3_png,金币底4_png,客服_png,龙虎_png,牛牛_png,商城_png,上底_png,时时彩_png,送金币_png,提现_png,头像框_png,头像适配大小_png,图层-21_png,推广_png,推筒子_png,下底_png,幸运飞艇_png,邮件_png,余额宝_png,真人视讯_png",
			"name": "preload"
		}
	],
	"resources": [
		{
			"url": "config/description.json",
			"type": "json",
			"name": "description_json"
		},
		{
			"url": "assets/btn/close.png",
			"type": "image",
			"name": "close_png"
		},
		{
			"url": "assets/btn/back_1.png",
			"type": "image",
			"name": "back_1_png"
		},
		{
			"name": "1_png",
			"type": "image",
			"url": "assets/btn/1.png"
		},
		{
			"name": "2_png",
			"type": "image",
			"url": "assets/btn/2.png"
		},
		{
			"name": "3_png",
			"type": "image",
			"url": "assets/btn/3.png"
		},
		{
			"name": "4_png",
			"type": "image",
			"url": "assets/btn/4.png"
		},
		{
			"name": "5_png",
			"type": "image",
			"url": "assets/btn/5.png"
		},
		{
			"name": "logo_png",
			"type": "image",
			"url": "assets/mui/logo.png"
		},
		{
			"name": "12_png",
			"type": "image",
			"url": "assets/mui/标注示意/1.png"
		},
		{
			"name": "22_png",
			"type": "image",
			"url": "assets/mui/标注示意/2.png"
		},
		{
			"name": "adLogin_png",
			"type": "image",
			"url": "assets/mui/adLogin.png"
		},
		{
			"name": "beijing_jpg",
			"type": "image",
			"url": "assets/mui/beijing.jpg"
		},
		{
			"name": "fastLogin_png",
			"type": "image",
			"url": "assets/mui/fastLogin.png"
		},
		{
			"name": "kefu_png",
			"type": "image",
			"url": "assets/mui/kefu.png"
		},
		{
			"name": "loading1_png",
			"type": "image",
			"url": "assets/mui/loading1.png"
		},
		{
			"name": "loading2_png",
			"type": "image",
			"url": "assets/mui/loading2.png"
		},
		{
			"name": "示意标注_png",
			"type": "image",
			"url": "assets/mui/标注示意/示意标注.png"
		},
		{
			"name": "13_png",
			"type": "image",
			"url": "assets/mui/help/1.png"
		},
		{
			"name": "23_png",
			"type": "image",
			"url": "assets/mui/help/2.png"
		},
		{
			"name": "32_png",
			"type": "image",
			"url": "assets/mui/help/3.png"
		},
		{
			"name": "42_png",
			"type": "image",
			"url": "assets/mui/help/4.png"
		},
		{
			"name": "52_png",
			"type": "image",
			"url": "assets/mui/help/5.png"
		},
		{
			"name": "6_png",
			"type": "image",
			"url": "assets/mui/help/6.png"
		},
		{
			"name": "help_png",
			"type": "image",
			"url": "assets/mui/help/help.png"
		},
		{
			"name": "zha_png",
			"type": "image",
			"url": "assets/mui/zha.png"
		},
		{
			"name": "打牌2_png",
			"type": "image",
			"url": "assets/mui/标注示意/打牌2.png"
		},
		{
			"name": "打牌1_png",
			"type": "image",
			"url": "assets/mui/标注示意/打牌1.png"
		},
		{
			"name": "cm1_png",
			"type": "image",
			"url": "assets/mui/game/cm1.png"
		},
		{
			"name": "cm2_png",
			"type": "image",
			"url": "assets/mui/game/cm2.png"
		},
		{
			"name": "cm3_png",
			"type": "image",
			"url": "assets/mui/game/cm3.png"
		},
		{
			"name": "cm4_png",
			"type": "image",
			"url": "assets/mui/game/cm4.png"
		},
		{
			"name": "cm5_png",
			"type": "image",
			"url": "assets/mui/game/cm5.png"
		},
		{
			"name": "cm6_png",
			"type": "image",
			"url": "assets/mui/game/cm6.png"
		},
		{
			"name": "cm7_png",
			"type": "image",
			"url": "assets/mui/game/cm7.png"
		},
		{
			"name": "cm8_png",
			"type": "image",
			"url": "assets/mui/game/cm8.png"
		},
		{
			"name": "WIN_png",
			"type": "image",
			"url": "assets/mui/game/WIN.png"
		},
		{
			"name": "倒计时_png",
			"type": "image",
			"url": "assets/mui/game/倒计时.png"
		},
		{
			"name": "切换房间_png",
			"type": "image",
			"url": "assets/mui/game/切换房间.png"
		},
		{
			"name": "发 送_png",
			"type": "image",
			"url": "assets/mui/game/发 送.png"
		},
		{
			"name": "广播_png",
			"type": "image",
			"url": "assets/mui/game/广播.png"
		},
		{
			"name": "广播底_png",
			"type": "image",
			"url": "assets/mui/game/广播底.png"
		},
		{
			"name": "庄平倍_png",
			"type": "image",
			"url": "assets/mui/game/庄平倍.png"
		},
		{
			"name": "庄翻倍_png",
			"type": "image",
			"url": "assets/mui/game/庄翻倍.png"
		},
		{
			"name": "无牛_png",
			"type": "image",
			"url": "assets/mui/game/无牛.png"
		},
		{
			"name": "筹码底_png",
			"type": "image",
			"url": "assets/mui/game/筹码底.png"
		},
		{
			"name": "筹码选中光_png",
			"type": "image",
			"url": "assets/mui/game/筹码选中光.png"
		},
		{
			"name": "箭头1_png",
			"type": "image",
			"url": "assets/mui/game/箭头1.png"
		},
		{
			"name": "箭头2_png",
			"type": "image",
			"url": "assets/mui/game/箭头2.png"
		},
		{
			"name": "结算中_png",
			"type": "image",
			"url": "assets/mui/game/结算中.png"
		},
		{
			"name": "聊天_png",
			"type": "image",
			"url": "assets/mui/game/聊天.png"
		},
		{
			"name": "聊天底_png",
			"type": "image",
			"url": "assets/mui/game/聊天底.png"
		},
		{
			"name": "蓝_png",
			"type": "image",
			"url": "assets/mui/game/蓝.png"
		},
		{
			"name": "表情_png",
			"type": "image",
			"url": "assets/mui/game/表情.png"
		},
		{
			"name": "规则_png",
			"type": "image",
			"url": "assets/mui/game/规则.png"
		},
		{
			"name": "视频_png",
			"type": "image",
			"url": "assets/mui/game/视频.png"
		},
		{
			"name": "设置_png",
			"type": "image",
			"url": "assets/mui/game/设置.png"
		},
		{
			"name": "路子图_png",
			"type": "image",
			"url": "assets/mui/game/路子图.png"
		},
		{
			"name": "路子图2_png",
			"type": "image",
			"url": "assets/mui/game/路子图2.png"
		},
		{
			"name": "返回底_png",
			"type": "image",
			"url": "assets/mui/game/返回底.png"
		},
		{
			"name": "金币_png",
			"type": "image",
			"url": "assets/mui/game/金币.png"
		},
		{
			"name": "金币底_png",
			"type": "image",
			"url": "assets/mui/game/金币底.png"
		},
		{
			"name": "问号_png",
			"type": "image",
			"url": "assets/mui/game/问号.png"
		},
		{
			"name": "闲1平倍_png",
			"type": "image",
			"url": "assets/mui/game/闲1平倍.png"
		},
		{
			"name": "闲1翻倍_png",
			"type": "image",
			"url": "assets/mui/game/闲1翻倍.png"
		},
		{
			"name": "闲2平倍_png",
			"type": "image",
			"url": "assets/mui/game/闲2平倍.png"
		},
		{
			"name": "闲2翻倍_png",
			"type": "image",
			"url": "assets/mui/game/闲2翻倍.png"
		},
		{
			"name": "闲3平倍_png",
			"type": "image",
			"url": "assets/mui/game/闲3平倍.png"
		},
		{
			"name": "闲3翻倍_png",
			"type": "image",
			"url": "assets/mui/game/闲3翻倍.png"
		},
		{
			"name": "黄_png",
			"type": "image",
			"url": "assets/mui/game/黄.png"
		},
		{
			"name": "圆角矩形 666 拷贝 4_png",
			"type": "image",
			"url": "assets/mui/login/圆角矩形 666 拷贝 4.png"
		},
		{
			"name": "登 录_png",
			"type": "image",
			"url": "assets/mui/login/登 录.png"
		},
		{
			"name": "登录_png",
			"type": "image",
			"url": "assets/mui/login/登录.png"
		},
		{
			"name": "获取验证码_png",
			"type": "image",
			"url": "assets/mui/login/获取验证码.png"
		},
		{
			"name": "标注_png",
			"type": "image",
			"url": "assets/mui/标注示意/标注.png"
		},
		{
			"name": "设置标注_png",
			"type": "image",
			"url": "assets/mui/标注示意/设置标注.png"
		},
		{
			"name": "音乐_png",
			"type": "image",
			"url": "assets/mui/setting/音乐.png"
		},
		{
			"name": "X_png",
			"type": "image",
			"url": "assets/mui/setting/X.png"
		},
		{
			"name": "底_png",
			"type": "image",
			"url": "assets/mui/setting/底.png"
		},
		{
			"name": "点_png",
			"type": "image",
			"url": "assets/mui/setting/点.png"
		},
		{
			"name": "聊天 copy_png",
			"type": "image",
			"url": "assets/mui/setting/聊天 copy.png"
		},
		{
			"name": "设置标注2_png",
			"type": "image",
			"url": "assets/mui/setting/设置标注.png"
		},
		{
			"name": "声音_png",
			"type": "image",
			"url": "assets/mui/setting/声音.png"
		},
		{
			"name": "视频2_png",
			"type": "image",
			"url": "assets/mui/setting/视频.png"
		},
		{
			"name": "系统设置_png",
			"type": "image",
			"url": "assets/mui/setting/系统设置.png"
		},
		{
			"name": "现场_png",
			"type": "image",
			"url": "assets/mui/setting/现场.png"
		},
		{
			"name": "小弹窗通用底_png",
			"type": "image",
			"url": "assets/mui/setting/小弹窗通用底.png"
		},
		{
			"name": "选房间标注_png",
			"type": "image",
			"url": "assets/mui/标注示意/选房间标注.png"
		},
		{
			"name": "限红_png",
			"type": "image",
			"url": "assets/mui/joinRoom/限红.png"
		},
		{
			"name": "jinbi_png",
			"type": "image",
			"url": "assets/mui/joinRoom/jinbi.png"
		},
		{
			"name": "底2_png",
			"type": "image",
			"url": "assets/mui/joinRoom/底.png"
		},
		{
			"name": "金币底2_png",
			"type": "image",
			"url": "assets/mui/joinRoom/金币底.png"
		},
		{
			"name": "开始_png",
			"type": "image",
			"url": "assets/mui/joinRoom/开始.png"
		},
		{
			"name": "头像底_png",
			"type": "image",
			"url": "assets/mui/joinRoom/头像底.png"
		},
		{
			"name": "图层 602_png",
			"type": "image",
			"url": "assets/mui/joinRoom/图层 602.png"
		},
		{
			"name": "选择房间3_png",
			"type": "image",
			"url": "assets/mui/标注示意/选择房间3.png"
		},
		{
			"name": "选择房间1_png",
			"type": "image",
			"url": "assets/mui/标注示意/选择房间1.png"
		},
		{
			"name": "选择房间2_png",
			"type": "image",
			"url": "assets/mui/标注示意/选择房间2.png"
		},
		{
			"name": "和_png",
			"type": "image",
			"url": "assets/mui/chooseRoom/百家乐龙虎/和.png"
		},
		{
			"name": "大_png",
			"type": "image",
			"url": "assets/mui/chooseRoom/百家乐龙虎/大.png"
		},
		{
			"name": "大1_png",
			"type": "image",
			"url": "assets/mui/chooseRoom/百家乐龙虎/大1.png"
		},
		{
			"name": "小1_png",
			"type": "image",
			"url": "assets/mui/chooseRoom/百家乐龙虎/小1.png"
		},
		{
			"name": "小2_png",
			"type": "image",
			"url": "assets/mui/chooseRoom/百家乐龙虎/小2.png"
		},
		{
			"name": "小圈_png",
			"type": "image",
			"url": "assets/mui/chooseRoom/百家乐龙虎/小圈.png"
		},
		{
			"name": "小圈2_png",
			"type": "image",
			"url": "assets/mui/chooseRoom/百家乐龙虎/小圈2.png"
		},
		{
			"name": "小红_png",
			"type": "image",
			"url": "assets/mui/chooseRoom/百家乐龙虎/小红.png"
		},
		{
			"name": "小蓝_png",
			"type": "image",
			"url": "assets/mui/chooseRoom/百家乐龙虎/小蓝.png"
		},
		{
			"name": "庄_png",
			"type": "image",
			"url": "assets/mui/chooseRoom/百家乐龙虎/庄.png"
		},
		{
			"name": "斜杠_png",
			"type": "image",
			"url": "assets/mui/chooseRoom/百家乐龙虎/斜杠.png"
		},
		{
			"name": "闲_png",
			"type": "image",
			"url": "assets/mui/chooseRoom/百家乐龙虎/闲.png"
		},
		{
			"name": "龙虎百家乐底_png",
			"type": "image",
			"url": "assets/mui/chooseRoom/百家乐龙虎/龙虎百家乐底.png"
		},
		{
			"name": "14_png",
			"type": "image",
			"url": "assets/mui/chooseRoom/大小点/1.png"
		},
		{
			"name": "24_png",
			"type": "image",
			"url": "assets/mui/chooseRoom/大小点/2.png"
		},
		{
			"name": "33_png",
			"type": "image",
			"url": "assets/mui/chooseRoom/大小点/3.png"
		},
		{
			"name": "43_png",
			"type": "image",
			"url": "assets/mui/chooseRoom/大小点/4.png"
		},
		{
			"name": "53_png",
			"type": "image",
			"url": "assets/mui/chooseRoom/大小点/5.png"
		},
		{
			"name": "62_png",
			"type": "image",
			"url": "assets/mui/chooseRoom/大小点/6.png"
		},
		{
			"name": "大小点底_png",
			"type": "image",
			"url": "assets/mui/chooseRoom/大小点/大小点底.png"
		},
		{
			"name": "WIN2_png",
			"type": "image",
			"url": "assets/mui/chooseRoom/牛牛推筒子/WIN.png"
		},
		{
			"name": "庄2_png",
			"type": "image",
			"url": "assets/mui/chooseRoom/牛牛推筒子/庄.png"
		},
		{
			"name": "底3_png",
			"type": "image",
			"url": "assets/mui/chooseRoom/牛牛推筒子/底.png"
		},
		{
			"name": "没牛底_png",
			"type": "image",
			"url": "assets/mui/chooseRoom/牛牛推筒子/没牛底.png"
		},
		{
			"name": "牛N底_png",
			"type": "image",
			"url": "assets/mui/chooseRoom/牛牛推筒子/牛N底.png"
		},
		{
			"name": "牛牛底_png",
			"type": "image",
			"url": "assets/mui/chooseRoom/牛牛推筒子/牛牛底.png"
		},
		{
			"name": "闲1_png",
			"type": "image",
			"url": "assets/mui/chooseRoom/牛牛推筒子/闲1.png"
		},
		{
			"name": "闲2_png",
			"type": "image",
			"url": "assets/mui/chooseRoom/牛牛推筒子/闲2.png"
		},
		{
			"name": "闲3_png",
			"type": "image",
			"url": "assets/mui/chooseRoom/牛牛推筒子/闲3.png"
		},
		{
			"name": "WIN1_png",
			"type": "image",
			"url": "assets/mui/chooseRoom/炸金花/WIN1.png"
		},
		{
			"name": "凤_png",
			"type": "image",
			"url": "assets/mui/chooseRoom/炸金花/凤.png"
		},
		{
			"name": "凤2_png",
			"type": "image",
			"url": "assets/mui/chooseRoom/炸金花/凤2.png"
		},
		{
			"name": "椭圆 1310 拷贝 2_png",
			"type": "image",
			"url": "assets/mui/chooseRoom/炸金花/椭圆 1310 拷贝 2.png"
		},
		{
			"name": "椭圆 1310_png",
			"type": "image",
			"url": "assets/mui/chooseRoom/炸金花/椭圆 1310.png"
		},
		{
			"name": "炸金花_png",
			"type": "image",
			"url": "assets/mui/chooseRoom/炸金花/炸金花.png"
		},
		{
			"name": "龙_png",
			"type": "image",
			"url": "assets/mui/chooseRoom/炸金花/龙.png"
		},
		{
			"name": "龙2_png",
			"type": "image",
			"url": "assets/mui/chooseRoom/炸金花/龙2.png"
		},
		{
			"name": "按钮_png",
			"type": "image",
			"url": "assets/mui/chooseRoom/按钮.png"
		},
		{
			"name": "结算中底_png",
			"type": "image",
			"url": "assets/mui/chooseRoom/结算中底.png"
		},
		{
			"name": "金币2_png",
			"type": "image",
			"url": "assets/mui/chooseRoom/金币.png"
		},
		{
			"name": "金币底3_png",
			"type": "image",
			"url": "assets/mui/chooseRoom/金币底.png"
		},
		{
			"name": "时间图标_png",
			"type": "image",
			"url": "assets/mui/chooseRoom/时间图标.png"
		},
		{
			"name": "头像适配_png",
			"type": "image",
			"url": "assets/mui/chooseRoom/头像适配.png"
		},
		{
			"name": "下注中底_png",
			"type": "image",
			"url": "assets/mui/chooseRoom/下注中底.png"
		},
		{
			"name": "选择房间_png",
			"type": "image",
			"url": "assets/mui/chooseRoom/选择房间.png"
		},
		{
			"name": "大厅标注_png",
			"type": "image",
			"url": "assets/mui/标注示意/大厅标注.png"
		},
		{
			"name": "0_png",
			"type": "image",
			"url": "assets/mui/hall/金币数字/0.png"
		},
		{
			"name": "15_png",
			"type": "image",
			"url": "assets/mui/hall/金币数字/1.png"
		},
		{
			"name": "25_png",
			"type": "image",
			"url": "assets/mui/hall/金币数字/2.png"
		},
		{
			"name": "34_png",
			"type": "image",
			"url": "assets/mui/hall/金币数字/3.png"
		},
		{
			"name": "44_png",
			"type": "image",
			"url": "assets/mui/hall/金币数字/4.png"
		},
		{
			"name": "54_png",
			"type": "image",
			"url": "assets/mui/hall/金币数字/5.png"
		},
		{
			"name": "63_png",
			"type": "image",
			"url": "assets/mui/hall/金币数字/6.png"
		},
		{
			"name": "7_png",
			"type": "image",
			"url": "assets/mui/hall/金币数字/7.png"
		},
		{
			"name": "8_png",
			"type": "image",
			"url": "assets/mui/hall/金币数字/8.png"
		},
		{
			"name": "9_png",
			"type": "image",
			"url": "assets/mui/hall/金币数字/9.png"
		},
		{
			"name": "d_png",
			"type": "image",
			"url": "assets/mui/hall/金币数字/d.png"
		},
		{
			"name": "+_png",
			"type": "image",
			"url": "assets/mui/hall/+.png"
		},
		{
			"name": "beijing2_jpg",
			"type": "image",
			"url": "assets/mui/hall/beijing.jpg"
		},
		{
			"name": "gb_png",
			"type": "image",
			"url": "assets/mui/hall/gb.png"
		},
		{
			"name": "VIP  _png",
			"type": "image",
			"url": "assets/mui/hall/VIP  .png"
		},
		{
			"name": "百家乐_png",
			"type": "image",
			"url": "assets/mui/hall/百家乐.png"
		},
		{
			"name": "绑定_png",
			"type": "image",
			"url": "assets/mui/hall/绑定.png"
		},
		{
			"name": "北京赛车_png",
			"type": "image",
			"url": "assets/mui/hall/北京赛车.png"
		},
		{
			"name": "大小点_png",
			"type": "image",
			"url": "assets/mui/hall/大小点.png"
		},
		{
			"name": "单双_png",
			"type": "image",
			"url": "assets/mui/hall/单双.png"
		},
		{
			"name": "公告_png",
			"type": "image",
			"url": "assets/mui/hall/公告.png"
		},
		{
			"name": "广告_png",
			"type": "image",
			"url": "assets/mui/hall/广告.png"
		},
		{
			"name": "广告点_png",
			"type": "image",
			"url": "assets/mui/hall/广告点.png"
		},
		{
			"name": "广告点选中_png",
			"type": "image",
			"url": "assets/mui/hall/广告点选中.png"
		},
		{
			"name": "滚动条底_png",
			"type": "image",
			"url": "assets/mui/hall/滚动条底.png"
		},
		{
			"name": "红点_png",
			"type": "image",
			"url": "assets/mui/hall/红点.png"
		},
		{
			"name": "滑动_png",
			"type": "image",
			"url": "assets/mui/hall/滑动.png"
		},
		{
			"name": "活动_png",
			"type": "image",
			"url": "assets/mui/hall/活动.png"
		},
		{
			"name": "金币3_png",
			"type": "image",
			"url": "assets/mui/hall/金币.png"
		},
		{
			"name": "金币底4_png",
			"type": "image",
			"url": "assets/mui/hall/金币底.png"
		},
		{
			"name": "客服_png",
			"type": "image",
			"url": "assets/mui/hall/客服.png"
		},
		{
			"name": "龙虎_png",
			"type": "image",
			"url": "assets/mui/hall/龙虎.png"
		},
		{
			"name": "牛牛_png",
			"type": "image",
			"url": "assets/mui/hall/牛牛.png"
		},
		{
			"name": "商城_png",
			"type": "image",
			"url": "assets/mui/hall/商城.png"
		},
		{
			"name": "上底_png",
			"type": "image",
			"url": "assets/mui/hall/上底.png"
		},
		{
			"name": "时时彩_png",
			"type": "image",
			"url": "assets/mui/hall/时时彩.png"
		},
		{
			"name": "送金币_png",
			"type": "image",
			"url": "assets/mui/hall/送金币.png"
		},
		{
			"name": "提现_png",
			"type": "image",
			"url": "assets/mui/hall/提现.png"
		},
		{
			"name": "头像框_png",
			"type": "image",
			"url": "assets/mui/hall/头像框.png"
		},
		{
			"name": "头像适配大小_png",
			"type": "image",
			"url": "assets/mui/hall/头像适配大小.png"
		},
		{
			"name": "图层-21_png",
			"type": "image",
			"url": "assets/mui/hall/图层-21.png"
		},
		{
			"name": "推广_png",
			"type": "image",
			"url": "assets/mui/hall/推广.png"
		},
		{
			"name": "推筒子_png",
			"type": "image",
			"url": "assets/mui/hall/推筒子.png"
		},
		{
			"name": "下底_png",
			"type": "image",
			"url": "assets/mui/hall/下底.png"
		},
		{
			"name": "幸运飞艇_png",
			"type": "image",
			"url": "assets/mui/hall/幸运飞艇.png"
		},
		{
			"name": "邮件_png",
			"type": "image",
			"url": "assets/mui/hall/邮件.png"
		},
		{
			"name": "余额宝_png",
			"type": "image",
			"url": "assets/mui/hall/余额宝.png"
		},
		{
			"name": "真人视讯_png",
			"type": "image",
			"url": "assets/mui/hall/真人视讯.png"
		}
	]
}